Workbook

Sheet Historic_Data
A1: Name | B1: Project Name | C1: Category | D1: Type | E1: First Date Designed | F1: Last Date Designed | G1: First Date Invoiced | H1: Last Date Invoiced | I1: Gestation Period (DAYS) | J1: Invoicing spread (DAYS) | K1: Account Mirror | L1: Product Mirror
A2: 18038 | B2: Building 900, Chesterford Research Park, CB | C2: Health | D2: Refurbishment | E2: 46090 | F2: 46090 | G2: 46106 | H2: 46106 | I2: 16 | J2: 0 | K2: Cambridge Roofers Ltd | L2: Tissue Faced PIR
A3: 17999 | B3: Argyle works, G | C3: Apartments | D3: New Build | E3: 46083 | F3: 46083 | G3: 46085 | H3: 46085 | I3: 2 | J3: 0 | K3: Jackson & Dix Roofing Ltd | L3: Tissue Faced PIR
A4: 18002 | B4: Bawtry Park, S | C4: Commercial | D4: Refurbishment | E4: 46084 | F4: 46084 | G4: 46101 | H4: 46101 | I4: 17 | J4: 0 | K4: M.K.M Building Supplies (Holdings) Limited | L4: Foil Faced PIR
A5: 17981 | B5: Bannatyne Health Club & Spa Briar Ln, Mansfield, NG | C5: Health | D5: Refurbishment | E5: 46079 | F5: 46079 | G5: 46090 | H5: 46090 | I5: 11 | J5: 0 | K5: FATRA UK LTD | L5: Tissue Faced PIR
A6: 17966 | B6: Random close, SG | C6: House | D6: Refurbishment | E6: 46076 | F6: 46078 | G6: 46106 | H6: 46106 | I6: 30 | J6: 0 | K6: EPD Insulation Group Ltd, EPD Insulation Group Ltd | L6: Tissue Faced PIR, Tissue Faced PIR
A7: 17955 | B7: Tudor Academy CR | C7: Education | D7: Refurbishment | E7: 46071 | F7: 46071 | G7: 46112 | H7: 46112 | I7: 41 | J7: 0 | K7: Langley Waterproofing Systems Limited | L7: Tissue Faced PIR
A8: 17947 | B8: Balcombe Breeze BH | C8: Apartments | D8: New Build | E8: 46070 | F8: 46070 | G8: 46078 | H8: 46078 | I8: 8 | J8: 0 | K8: Williams Roofing Contracts Limited | L8: Tissue Faced PIR
A9: 17943 | B9: 39 Highfield Avenue, BR | C9: Apartments | D9: Refurbishment | E9: 46069 | F9: 46069 | G9: 46108 | H9: 46108 | I9: 39 | J9: 0 | K9: Alltype Roofing Supplies Ltd | L9: Torch On PIR
A10: 17931 | B10: SESS, Cramlington, NE | C10: Apartments | D10: Refurbishment | E10: 46065 | F10: 46065 | G10: 46090 | H10: 46090 | I10: 25 | J10: 0 | K10: Lancastria LLP | L10: Torch On PIR
A11: 17909 | B11: Berrylands court Sutton | C11: Apartments | D11: Refurbishment | E11: 46062 | F11: 46072 | G11: 46080 | H11: 46080 | I11: 18 | J11: 0 | K11: Westwood Liquid Technologies Limited, Westwood Liquid Technologies Limited | L11: Tissue Faced PIR, Tissue Faced PIR
A12: 17892 | B12: GO Ebbw Vale | C12: Commercial | D12: Refurbishment | E12: 46057 | F12: 46057 | G12: 46083 | H12: 46083 | I12: 26 | J12: 0 | K12: A.Baul Roofing | L12: Tissue Faced PIR
A13: 17839 | B13: 41 Clarendon Road, London W11 | C13: Apartments | D13: New Build | E13: 46044 | F13: 46044 | G13: 46063 | H13: 46063 | I13: 19 | J13: 0 | K13: ICB (Waterproofing) Ltd | L13: Tissue Faced PIR, VIPs
... A352: 14934 | B352: North West Cambridge - Lot 4 Residential Development, CB | C352: Apartments | D352: New Build | E352: 45454 | F352: 45456 | G352: 45488 | H352: 45488 | I352: 34 | J352: 0 | K352: Axter Limited, Axter Limited | L352: Tissue Faced PIR, Tissue Faced PIR
A353: 14930 | B353: 6 The Boltons Kensington | C353: Apartments | D353: New Build | G353: 45468 | H353: 45468 | I353: 16 | J353: 0 | K353: Garhigh (Southern) Limited | L353: VIPs
A354: 14923 | B354: Unit 28, Minworth, B | C354: Industrial | D354: Refurbishment | E354: 45453 | F354: 45453 | G354: 45573 | H354: 45597 | I354: 120 | J354: 24 | K354: Axter Limited, Axter Limited, Axter Limited | L354: Tissue Faced PIR
A355: 14901 | B355: Aurora, Trawler Road, SA | C355: Apartments | D355: New Build | E355: 45450 | F355: 46101 | G355: 45505 | H355: 45537 | I355: 55 | J355: 32 | K355: Rockwool Limited (Bauder), Rockwool Limited (Bauder), Rockwool Limited (Bauder), Rockwool Limited (Bauder), Rockwool Limited (Bauder), Rockwool Limited (Bauder), Rockwool Limited (Bauder), Rockwool Limited (Bauder), Rockwool Limited (Bauder), Rockwool Limited (Bauder) | L355: ROCKWOOL HardRock Multi-Fix (DD), ROCKWOOL HardRock Multi-Fix (DD), ROCKWOOL HardRock Multi-Fix (DD), ROCKWOOL HardRock Multi-Fix (DD), ROCKWOOL HardRock Multi-Fix (DD), ROCKWOOL HardRock Multi-Fix (DD), ROCKWOOL HardRock Multi-Fix (DD)
A356: 14898 | B356: Forster Park, North Road | C356: Apartments | D356: New Build | E356: 45449 | F356: 45449 | G356: 45824 | H356: 45824 | I356: 375 | J356: 0 | K356: Axter Limited | L356: Tissue Faced PIR
A357: 14895 | B357: 6 Broughton Gardens, N6 5RS | C357: Health | D357: New Build | E357: 45449 | F357: 45621 | G357: 45789 | H357: 45789 | I357: 340 | J357: 0 | K357: Moy Materials (UK) Limited, Moy Materials (UK) Limited, Moy Materials (UK) Limited, Quantum Insulation | L357: Inverted EPS, Inverted EPS, Inverted EPS, Inverted EPS
A358: 14894 | B358: Ysgol Cynefin, CF | C358: Apartments | D358: New Build | E358: 45450 | F358: 45862 | G358: 45806 | H358: 45867 | I358: 356 | J358: 61 | K358: Alumasc Building Products Limited, Alumasc Building Products Limited, Alumasc Building Products Limited, Alumasc Building Products Limited, Alumasc Building Products Limited, Alumasc Building Products Limited, Alumasc Building Products Limited, Alumasc Building Products Limited, Alumasc Building Products Limited, Alumasc Building Products Limited, Alumasc Building Products Limited, Alumasc Building Products Limited | L358: ROCKWOOL HardRock Multi-Fix (DD), ROCKWOOL HardRock Multi-Fix (DD), ROCKWOOL HardRock Multi-Fix (DD), ROCKWOOL HardRock Multi-Fix (DD), ROCKWOOL HardRock Multi-Fix (DD), ROCKWOOL HardRock Multi-Fix (DD), ROCKWOOL HardRock Multi-Fix (DD), ROCKWOOL HardRock Multi-Fix (DD), ROCKWOOL HardRock Multi-Fix (DD), ROCKWOOL HardRock Multi-Fix (DD), ROCKWOOL HardRock Multi-Fix (DD), ROCKWOOL HardRock Multi-Fix (DD)
A359: 14888 | B359: 14 Craven Hill Mews | C359: Apartments | D359: New Build | E359: 45448 | F359: 46077 | G359: 46097 | H359: 46097 | I359: 649 | J359: 0 | K359: ICB (Waterproofing) Ltd, ICB (Waterproofing) Ltd, ICB (Waterproofing) Ltd, ICB (Waterproofing) Ltd, ICB (Waterproofing) Ltd, ICB (Waterproofing) Ltd, ICB (Waterproofing) Ltd, ICB (Waterproofing) Ltd, ICB (Waterproofing) Ltd, ICB (Waterproofing) Ltd, ICB (Waterproofing) Ltd | L359: Tissue Faced PIR (Prebonded), Tissue Faced PIR, Tissue Faced PIR, Tissue Faced PIR, VIPs, Tissue Faced PIR, VIPs, Tissue Faced PIR (Prebonded), VIPs, VIPs, Tissue Faced PIR (Prebonded), Tissue Faced PIR, VIPs
A360: 14880 | B360: Harrods London | C360: Apartments | D360: New Build | E360: 45448 | F360: 45450 | G360: 45617 | H360: 45617 | I360: 169 | J360: 0 | K360: Rockwool Limited (Bauder), Rockwool Limited (Bauder) | L360: ROCKWOOL HardRock Multi-Fix (DD), ROCKWOOL HardRock Multi-Fix (DD)
A361: 14870 | B361: Cornmill House, Spring Gardens, Romford, London | C361: Apartments | D361: New Build | E361: 45447 | F361: 45485 | G361: 45517 | H361: 45518 | I361: 70 | J361: 1 | K361: Bluestage Ltd, Bluestage Ltd, Bluestage Ltd, Bluestage Ltd, Bluestage Ltd, Bluestage Ltd, Bluestage Ltd | L361: Foil Faced PIR, Foil Faced PIR, Foil Faced PIR, Tissue Faced PIR
A362: 14869 | B362: Launceston college, PL | C362: Education | D362: Refurbishment | E362: 45447 | F362: 45448 | G362: 45481 | H362: 45496 | I362: 34 | J362: 15 | K362: Garland, Garland, Garland, Garland, Garland | L362: EPS / PIR Torch On (Prebonded), EPS / PIR Torch On (Prebonded)
A363: 14865 | B363: Leicester Road, Market Harborough, Leicestershire, LE16 7AY | C363: House | D363: Refurbishment | E363: 45447 | F363: 45457 | G363: 45495 | H363: 45495 | I363: 48 | J363: 0 | K363: Triflex (U.K.) Limited, Triflex (U.K.) Limited | L363: Tissue Faced PIR, Tissue Faced PIR
A364: 14862 | B364: New Bond Street, W | C364: Apartments | D364: Refurbishment | E364: 45446 | F364: 45446 | G364: 45449 | H364: 45449 | I364: 3 | J364: 0 | K364: Kent Asphalt Ltd | L364: Tissue Faced PIR
A365: 14858 | B365: Blindwells Primary School | C365: Education | D365: Refurbishment | E365: 45446 | F365: 45623 | G365: 45499 | H365: 45691 | I365: 53 | J365: 192 | K365: Rockwool Limited (Bauder), Rockwool Limited (Bauder) | L365: ROCKWOOL HardRock Multi-Fix (DD), ROCKWOOL HardRock Multi-Fix (DD)
... A683: 43 | B683: Bromley-by-Bow Phase 2 | C683: 16 | D683: 16 | E683: 42035 | F683: 45455 | G683: 45460 | H683: 45460 | I683: 3425 | J683: 0 | K683: U Value Insulation Limited, U Value Insulation Limited, Southern Mastic Roofing, Southern Mastic Roofing, Southern Mastic Roofing | L683: EPS/PIR Tissue Faced, EPS/PIR Tissue Faced, Tissue Faced PIR

Sheet Dashboard
A1: Smoothing Adoption Model
A2: Built from the historic project workbook. Default predictive views use a 180-day mature cohort cut-off: first invoice on or before 2025-10-30.
A3: Metric | B3: All Projects | C3: 180-day Mature Cohort | D3: 365-day Sensitivity | F3: Interpretation | J3: Signal | K3: Shrunk Smoothed % | L3: Expected Days
A4: Project count | B4: 682 | C4: 568 | D4: 408 | F4: Use the mature cohort for future smoothing because very recent projects are censored. | J4: Torch On PIR (Prebonded) | K4: 0.64412336 | L4: 175.61875
A5: Smoothed projects | B5: 244 | C5: 209 | D5: 157 | F5: A project is smoothed when invoice spread days are greater than zero. | J5: EPS / PIR Torch On (Prebonded) | K5: 0.59879867 | L5: 162.26139
A6: Smoothed % | B6: 0.35777126 | C6: 0.36795775 | D6: 0.38480392 | F6: Observed probability that a project invoices across more than one date. | J6: Garland | K6: 0.70284205 | L6: 160.23013
A7: Avg spread, all projects | B7: 68.347507 | C7: 78.394366 | D7: 98.97549 | F7: Expected spread across the whole portfolio including same-day projects. | J7: Rockwool Limited | K7: 0.4743618 | L7: 145.29511
A8: Avg spread, smoothed only | B8: 191.03689 | C8: 213.05263 | D8: 257.21019 | F8: Typical duration once smoothing actually occurs. | J8: Moy Materials (UK) Limited | K8: 0.47346872 | L8: 141.62529
A9: Median spread, smoothed only | B9: 91 | C9: 112 | D9: 162 | F9: The central smoothed-project invoice lag. | J9: Tissue Faced PIR (Prebonded) | K9: 0.39650949 | L9: 135.65054
A10: P75 spread, smoothed only | B10: 225.25 | C10: 256 | D10: 367 | F10: Use for prudent cashflow phasing where smoothing risk is high. | J10: ROCKWOOL HardRock Multi-Fix (D | K10: 0.42898402 | L10: 121.35892
A11: P90 spread, smoothed only | B11: 522.4 | C11: 567.2 | D11: 630.8 | F11: Use for downside / delayed billing sensitivity. | J11: Axter Limited | K11: 0.49273347 | L11: 120.15215
A13: Highest-value smoothing signals for future adoption
A14: Dimension | B14: Group | C14: Mature Projects | D14: Shrunk Smoothed % | E14: Expected Spread Days | F14: 90+ Day Rate | G14: 180+ Day Rate | H14: Confidence
A15: Product | B15: Torch On PIR (Prebonded) | C15: 38 | D15: 0.64412336 | E15: 175.61875 | F15: 0.55263158 | G15: 0.39473684 | H15: Medium | Adopt smoothing by default
A16: Product | B16: EPS / PIR Torch On (Prebonded) | C16: 14 | D16: 0.59879867 | E16: 162.26139 | F16: 0.71428571 | G16: 0.57142857 | H16: Low | Adopt smoothing by default
A17: Account | B17: Garland | C17: 36 | D17: 0.70284205 | E17: 160.23013 | F17: 0.52777778 | G17: 0.38888889 | H17: Medium | Adopt smoothing by default
A18: Account | B18: Rockwool Limited | C18: 44 | D18: 0.4743618 | E18: 145.29511 | F18: 0.43181818 | G18: 0.38636364 | H18: Medium | Adopt smoothing by default
A19: Account | B19: Moy Materials (UK) Limited | C19: 23 | D19: 0.47346872 | E19: 141.62529 | F19: 0.47826087 | G19: 0.47826087 | H19: Medium | Adopt smoothing by default
A20: Product | B20: Tissue Faced PIR (Prebonded) | C20: 49 | D20: 0.39650949 | E20: 135.65054 | F20: 0.28571429 | G20: 0.2244898 | H20: Medium | Adopt smoothing by default
A21: Product | B21: ROCKWOOL HardRock Multi-Fix (DD) | C21: 158 | D21: 0.42898402 | E21: 121.35892 | F21: 0.30379747 | G21: 0.26582278 | H21: High | Adopt smoothing by default
A22: Account | B22: Axter Limited | C22: 137 | D22: 0.49273347 | E22: 120.15215 | F22: 0.34306569 | G22: 0.24087591 | H22: High | Adopt smoothing by default
A23: Category + Type | B23: Education | Refurbishment | C23: 77 | D23: 0.59133149 | E23: 116.66894 | F23: 0.31168831 | G23: 0.23376623 | H23: High | Adopt smoothing by default
A24: Product | B24: ROCKDeck | C24: 16 | D24: 0.48219875 | E24: 113.71909 | F24: 0.5 | G24: 0.375 | H24: Medium | Model smoothing scenario
A25: Category + Type | B25: Consultancy | New Build | C25: 11 | D25: 0.39868242 | E25: 108.41572 | F25: 0.36363636 | G25: 0.36363636 | H25: Low | Model smoothing scenario
A26: Category + Type | B26: Health | Refurbishment | C26: 12 | D26: 0.35497359 | E26: 108.09023 | F26: 0.16666667 | G26: 0.16666667 | H26: Low | Model smoothing scenario
... A29: Account | B29: ICB (Waterproofing) Ltd | C29: 30 | D29: 0.3071831 | E29: 104.91775 | F29: 0.16666667 | G29: 0.13333333 | H29: Medium | Model smoothing scenario

Sheet Category_Summary
A1: Category / sector smoothing summary
A2: Predictive columns use the 180-day mature cohort with shrinkage toward the portfolio average.
A4: Group | B4: All Projects | C4: All Smoothed % | D4: Mature Projects | E4: Mature Smoothed % | F4: Shrunk Mature Smoothed % | G4: Mature Expected Spread Days | H4: Avg Spread if Smoothed | I4: Median Smoothed Days | J4: P75 Smoothed Days | K4: 90+ Day Rate | L4: 180+ Day Rate | M4: Confidence | N4: Suggested Use
A5: Apartments | B5: 217 | C5: 0.36866359 | D5: 175 | E5: 0.36 | F5: 0.36081618 | G5: 83.937884 | H5: 234.92063 | I5: 157 | J5: 290 | K5: 0.25714286 | L5: 0.17142857 | M5: High | N5: Model smoothing scenario
A6: House | B6: 134 | C6: 0.20149254 | D6: 108 | E6: 0.17592593 | F6: 0.2059309 | G6: 39.170995 | H6: 181.36842 | I6: 98 | J6: 184 | K6: 0.092592593 | L6: 0.046296296 | M6: High | N6: No default smoothing
A7: Education | B7: 117 | C7: 0.52136752 | D7: 104 | E7: 0.54807692 | F7: 0.51902544 | G7: 103.60393 | H7: 197.87719 | I7: 80 | J7: 234 | K7: 0.25 | L7: 0.18269231 | M7: High | N7: Model smoothing scenario
A8: Commercial | B8: 73 | C8: 0.30136986 | D8: 63 | E8: 0.34920635 | F8: 0.35372476 | G8: 62.335992 | H8: 163.90909 | I8: 79.5 | J8: 226.25 | K8: 0.15873016 | L8: 0.11111111 | M8: High | N8: Flag for review / light smoothing
A9: Health | B9: 46 | C9: 0.34782609 | D9: 34 | E9: 0.35294118 | F9: 0.35850287 | G9: 80.53495 | H9: 231.75 | I9: 63 | J9: 221.75 | K9: 0.14705882 | L9: 0.14705882 | M9: Medium | N9: Model smoothing scenario
A10: Leisure | B10: 36 | C10: 0.25 | D10: 31 | E10: 0.29032258 | F10: 0.32076774 | G10: 80.37034 | H10: 281.22222 | I10: 101 | J10: 299 | K10: 0.16129032 | L10: 0.12903226 | M10: Medium | N10: Model smoothing scenario
A11: Consultancy | B11: 13 | C11: 0.38461538 | D11: 13 | E11: 0.38461538 | F11: 0.37451985 | G11: 101.84507 | H11: 358.6 | I11: 395 | J11: 580 | K11: 0.30769231 | L11: 0.30769231 | M11: Low | N11: Model smoothing scenario
A12: Industrial | B12: 13 | C12: 0.23076923 | D12: 11 | E12: 0.27272727 | F12: 0.33416629 | G12: 52.41572 | H12: 19 | I12: 24 | J12: 24 | K12: 0 | L12: 0 | M12: Low | N12: Flag for review / light smoothing
A13: Datacentre | B13: 9 | C13: 0.44444444 | D13: 7 | E13: 0.42857143 | F13: 0.3836724 | G13: 91.255086 | H13: 298.66667 | I13: 243 | J13: 403.5 | K13: 0.28571429 | L13: 0.28571429 | M13: Low | N13: Model smoothing scenario
A14: Mixed Use | B14: 8 | C14: 0.625 | D14: 7 | E14: 0.57142857 | F14: 0.42070944 | G14: 89.440271 | H14: 211.75 | I14: 199 | J14: 394.5 | K14: 0.28571429 | L14: 0.28571429 | M14: Low | N14: Model smoothing scenario
A15: Commodity | B15: 6 | C15: 1 | D15: 6 | E15: 1 | F15: 0.51381365 | G15: 97.495666 | H15: 161.16667 | I15: 182 | J15: 210.25 | K15: 0.66666667 | L15: 0.5 | M15: Low | N15: Model smoothing scenario
A16: Military | B16: 4 | C16: 0.75 | D16: 4 | E16: 0.75 | F16: 0.43163146 | G16: 87.328638 | H16: 176 | I16: 65 | J16: 246 | K16: 0.25 | L16: 0.25 | M16: Very low | N16: Weak signal only
A17: Student Accommodation | B17: 2 | C17: 1 | D17: 2 | E17: 1 | F17: 0.42541613 | G17: 114.99488 | H17: 481 | I17: 481 | J17: 581.5 | K17: 1 | L17: 1 | M17: Very low | N17: Weak signal only
A18: Education, Commercial | B18: 1 | C18: 0 | D18: 0 | F18: 0.36795775 | G18: 78.394366 | H18: 0 | I18: 0 | J18: 0 | M18: Very low | N18: Weak signal only

Sheet Type_Summary
A1: Project type smoothing summary
A2: Type alone is a weak differentiator here; use it as a secondary signal.
A4: Group | B4: All Projects | C4: All Smoothed % | D4: Mature Projects | E4: Mature Smoothed % | F4: Shrunk Mature Smoothed % | G4: Mature Expected Spread Days | H4: Avg Spread if Smoothed | I4: Median Smoothed Days | J4: P75 Smoothed Days | K4: 90+ Day Rate | L4: 180+ Day Rate | M4: Confidence | N4: Suggested Use
A5: New Build | B5: 365 | C5: 0.35342466 | D5: 298 | E5: 0.3557047 | F5: 0.35647533 | G5: 84.443042 | H5: 238.53774 | I5: 163 | J5: 297.5 | K5: 0.22483221 | L5: 0.17114094 | M5: High | N5: Model smoothing scenario
A6: Refurbishment | B6: 314 | C6: 0.36305732 | D6: 267 | E6: 0.38202247 | F6: 0.38104235 | G6: 72.389851 | H6: 188.31373 | I6: 85.5 | J6: 209.25 | K6: 0.1835206 | L6: 0.12359551 | M6: High | N6: Flag for review / light smoothing

Sheet Category_Type_Summary
A1: Category plus type smoothing summary
A2: This is often more useful than type alone, especially for Education Refurbishment and Apartments New Build.
A4: Group | B4: All Projects | C4: All Smoothed % | D4: Mature Projects | E4: Mature Smoothed % | F4: Shrunk Mature Smoothed % | G4: Mature Expected Spread Days | H4: Avg Spread if Smoothed | I4: Median Smoothed Days | J4: P75 Smoothed Days | K4: 90+ Day Rate | L4: 180+ Day Rate | M4: Confidence | N4: Suggested Use
A5: Apartments | New Build | B5: 150 | C5: 0.40666667 | D5: 120 | E5: 0.40833333 | F5: 0.40256539 | G5: 101.98491 | H5: 259.38776 | I5: 184 | J5: 410 | K5: 0.3 | L5: 0.21666667 | M5: High | N5: Model smoothing scenario
A6: Education | Refurbishment | B6: 85 | C6: 0.62352941 | D6: 77 | E6: 0.64935065 | F6: 0.59133149 | G6: 116.66894 | H6: 194.98 | I6: 84 | J6: 248.25 | K6: 0.31168831 | L6: 0.23376623 | M6: High | N6: Adopt smoothing by default
A7: House | Refurbishment | B7: 73 | C7: 0.20547945 | D7: 59 | E7: 0.20338983 | F7: 0.24505259 | G7: 41.947941 | H7: 145.5 | I7: 46 | J7: 166.25 | K7: 0.084745763 | L7: 0.050847458 | M7: High | N7: No default smoothing
A8: Apartments | Refurbishment | B8: 67 | C8: 0.28358209 | D8: 55 | E8: 0.25454545 | F8: 0.28478873 | G8: 48.771831 | H8: 149.28571 | I8: 137.5 | J8: 181 | K8: 0.16363636 | L8: 0.072727273 | M8: High | N8: No default smoothing
A9: House | New Build | B9: 61 | C9: 0.19672131 | D9: 49 | E9: 0.14285714 | F9: 0.20810369 | G9: 47.360686 | H9: 242.85714 | I9: 120 | J9: 184 | K9: 0.10204082 | L9: 0.040816327 | M9: Medium | N9: No default smoothing
A10: Commercial | New Build | B10: 36 | C10: 0.38888889 | D10: 32 | E10: 0.4375 | F10: 0.41075298 | G10: 74.997833 | H10: 166.57143 | I10: 79.5 | J10: 226.25 | K10: 0.1875 | L10: 0.15625 | M10: Medium | N10: Flag for review / light smoothing
A11: Commercial | Refurbishment | B11: 37 | C11: 0.21621622 | D11: 31 | E11: 0.25806452 | F11: 0.3011599 | G11: 55.723281 | H11: 159.25 | I11: 116 | J11: 218.5 | K11: 0.12903226 | L11: 0.064516129 | M11: Medium | N11: Flag for review / light smoothing
A12: Education | New Build | B12: 32 | C12: 0.25 | D12: 27 | E12: 0.25925926 | F12: 0.30551393 | G12: 65.912496 | H12: 218.57143 | I12: 59 | J12: 92 | K12: 0.074074074 | L12: 0.037037037 | M12: Medium | N12: Flag for review / light smoothing
A13: Health | New Build | B13: 28 | C13: 0.39285714 | D13: 22 | E13: 0.36363636 | F13: 0.36569416 | G13: 58.521127 | H13: 111.25 | I13: 63 | J13: 199.75 | K13: 0.13636364 | L13: 0.13636364 | M13: Medium | N13: Flag for review / light smoothing
A14: Leisure | Refurbishment | B14: 19 | C14: 0.36842105 | D14: 19 | E14: 0.36842105 | F14: 0.36818346 | G14: 81.843265 | H14: 232 | I14: 73 | J14: 148.5 | K14: 0.15789474 | L14: 0.10526316 | M14: Medium | N14: Model smoothing scenario
A15: Health | Refurbishment | B15: 18 | C15: 0.27777778 | D15: 12 | E15: 0.33333333 | F15: 0.35497359 | G15: 108.09023 | H15: 472.75 | I15: 401 | J15: 857.5 | K15: 0.16666667 | L15: 0.16666667 | M15: Low | N15: Model smoothing scenario
A16: Leisure | New Build | B16: 17 | C16: 0.11764706 | D16: 12 | E16: 0.16666667 | F16: 0.29247359 | G16: 77.340229 | H16: 453.5 | I16: 453.5 | J16: 530.75 | K16: 0.16666667 | L16: 0.16666667 | M16: Low | N16: Flag for review / light smoothing
... A29: Military | Refurbishment | B29: 1 | C29: 1 | D29: 1 | E29: 1 | F29: 0.398055 | G29: 94.994634 | H29: 427 | I29: 427 | J29: 427 | K29: 1 | L29: 1 | M29: Very low | N29: Weak signal only
A30: Education, Commercial | Refurbishment | B30: 1 | C30: 0 | D30: 0 | F30: 0.36795775 | G30: 78.394366 | H30: 0 | I30: 0 | J30: 0 | M30: Very low | N30: Weak signal only

Sheet Product_Summary
A1: Product smoothing summary
A2: Products are parsed from Product Mirror and counted once per historic project when present.
A4: Group | B4: All Projects | C4: All Smoothed % | D4: Mature Projects | E4: Mature Smoothed % | F4: Shrunk Mature Smoothed % | G4: Mature Expected Spread Days | H4: Avg Spread if Smoothed | I4: Median Smoothed Days | J4: P75 Smoothed Days | K4: 90+ Day Rate | L4: 180+ Day Rate | M4: Confidence | N4: Suggested Use
A5: Tissue Faced PIR | B5: 432 | C5: 0.3587963 | D5: 349 | E5: 0.36962751 | F5: 0.36953701 | G5: 73.216497 | H5: 197.27907 | I5: 104 | J5: 231 | K5: 0.20057307 | L5: 0.13467049 | M5: High | N5: Flag for review / light smoothing
A6: ROCKWOOL HardRock Multi-Fix (DD) | B6: 193 | C6: 0.43523316 | D6: 158 | E6: 0.43670886 | F6: 0.42898402 | G6: 121.35892 | H6: 290.34783 | I6: 202 | J6: 395 | K6: 0.30379747 | L6: 0.26582278 | M6: High | N6: Adopt smoothing by default
A7: Torch On PIR | B7: 99 | C7: 0.50505051 | D7: 83 | E7: 0.51807229 | F7: 0.48892383 | G7: 96.629974 | H7: 195 | I7: 101 | J7: 257.5 | K7: 0.27710843 | L7: 0.21686747 | M7: High | N7: Model smoothing scenario
A8: Tissue Faced PIR (Prebonded) | B8: 54 | C8: 0.40740741 | D8: 49 | E8: 0.40816327 | F8: 0.39650949 | G8: 135.65054 | H8: 389.6 | I8: 221 | J8: 753.25 | K8: 0.28571429 | L8: 0.2244898 | M8: Medium | N8: Adopt smoothing by default
A9: VIPs | B9: 50 | C9: 0.46 | D9: 39 | E9: 0.46153846 | F9: 0.42981619 | G9: 87.896395 | H9: 201 | I9: 121.5 | J9: 189.75 | K9: 0.30769231 | L9: 0.12820513 | M9: Medium | N9: Model smoothing scenario
A10: Torch On PIR (Prebonded) | B10: 41 | C10: 0.7804878 | D10: 38 | E10: 0.78947368 | F10: 0.64412336 | G10: 175.61875 | H10: 287.26667 | I10: 185.5 | J10: 346.25 | K10: 0.55263158 | L10: 0.39473684 | M10: Medium | N10: Adopt smoothing by default
A11: Foil Faced PIR | B11: 45 | C11: 0.48888889 | D11: 37 | E11: 0.51351351 | F11: 0.46244131 | G11: 107.98048 | H11: 241.42105 | I11: 153 | J11: 361 | K11: 0.27027027 | L11: 0.24324324 | M11: Medium | N11: Model smoothing scenario
A12: ROCKDeck | B12: 17 | C12: 0.64705882 | D12: 16 | E12: 0.625 | F12: 0.48219875 | G12: 113.71909 | H12: 252.6 | I12: 203.5 | J12: 338 | K12: 0.5 | L12: 0.375 | M12: Medium | N12: Model smoothing scenario
A13: EPS / PIR Torch On (Prebonded) | B13: 14 | C13: 0.92857143 | D13: 14 | E13: 0.92857143 | F13: 0.59879867 | G13: 162.26139 | H13: 303.76923 | I13: 262 | J13: 379 | K13: 0.71428571 | L13: 0.57142857 | M13: Low | N13: Adopt smoothing by default
A14: EPS 150 (SPR) | B14: 14 | C14: 0.21428571 | D14: 14 | E14: 0.21428571 | F14: 0.30468103 | G14: 66.908451 | H14: 235.66667 | I14: 262 | J14: 336 | K14: 0.14285714 | L14: 0.14285714 | M14: Low | N14: Flag for review / light smoothing
A15: EPS/PIR Tissue Faced | B15: 11 | C15: 0.36363636 | D15: 9 | E15: 0.44444444 | F15: 0.391695 | G15: 90.271977 | H15: 262.5 | I15: 132 | J15: 337.5 | K15: 0.22222222 | L15: 0.22222222 | M15: Low | N15: Model smoothing scenario
A16: Roofblock G1T3+ | B16: 11 | C16: 0.45454545 | D16: 9 | E16: 0.44444444 | F16: 0.391695 | G16: 81.375425 | H16: 198 | I16: 196 | J16: 199.75 | K16: 0.44444444 | L16: 0.44444444 | M16: Low | N16: Model smoothing scenario
... A31: vip | B31: 1 | C31: 0 | D31: 1 | E31: 0 | F31: 0.35043595 | G31: 74.661301 | H31: 0 | I31: 0 | J31: 0 | K31: 0 | L31: 0 | M31: Very low | N31: Weak signal only
A32: ROCKDeck Coverboard | B32: 1 | C32: 0 | D32: 0 | F32: 0.36795775 | G32: 78.394366 | H32: 0 | I32: 0 | J32: 0 | M32: Very low | N32: Weak signal only

Sheet Account_Summary
A1: Account / customer smoothing summary
A2: Accounts are parsed from Account Mirror and counted once per historic project when present.
A4: Group | B4: All Projects | C4: All Smoothed % | D4: Mature Projects | E4: Mature Smoothed % | F4: Shrunk Mature Smoothed % | G4: Mature Expected Spread Days | H4: Avg Spread if Smoothed | I4: Median Smoothed Days | J4: P75 Smoothed Days | K4: 90+ Day Rate | L4: 180+ Day Rate | M4: Confidence | N4: Suggested Use
A5: Axter Limited | B5: 162 | C5: 0.50617284 | D5: 137 | E5: 0.51094891 | F5: 0.49273347 | G5: 120.15215 | H5: 247.08571 | I5: 162.5 | J5: 341.75 | K5: 0.34306569 | L5: 0.24087591 | M5: High | N5: Adopt smoothing by default
A6: Rockwool Limited (Bauder) | B6: 85 | C6: 0.31764706 | D6: 75 | E6: 0.32 | F6: 0.33009637 | G6: 106.19881 | H6: 355.04167 | I6: 192.5 | J6: 585.75 | K6: 0.21333333 | L6: 0.18666667 | M6: High | N6: Model smoothing scenario
A7: Rockwool Limited | B7: 51 | C7: 0.47058824 | D7: 44 | E7: 0.52272727 | F7: 0.4743618 | G7: 145.29511 | H7: 336.13043 | I7: 280 | J7: 388 | K7: 0.43181818 | L7: 0.38636364 | M7: Medium | N7: Adopt smoothing by default
A8: AccuRoof | B8: 44 | C8: 0.25 | D8: 38 | E8: 0.26315789 | F8: 0.29929577 | G8: 63.618747 | H8: 212.2 | I8: 95 | J8: 356.25 | K8: 0.13157895 | L8: 0.078947368 | M8: Medium | N8: Flag for review / light smoothing
A9: Garland | B9: 40 | C9: 0.875 | D9: 36 | E9: 0.88888889 | F9: 0.70284205 | G9: 160.23013 | H9: 231.40625 | I9: 140 | J9: 307.25 | K9: 0.52777778 | L9: 0.38888889 | M9: Medium | N9: Adopt smoothing by default
A10: ICB (Waterproofing) Ltd | B10: 39 | C10: 0.25641026 | D10: 30 | E10: 0.26666667 | F10: 0.3071831 | G10: 104.91775 | H10: 459.75 | I10: 315.5 | J10: 825 | K10: 0.16666667 | L10: 0.13333333 | M10: Medium | N10: Model smoothing scenario
A11: Langley Waterproofing Systems Limited | B11: 38 | C11: 0.44736842 | D11: 29 | E11: 0.48275862 | F11: 0.43590112 | G11: 77.507905 | H11: 159.28571 | I11: 125 | J11: 198.75 | K11: 0.27586207 | L11: 0.17241379 | M11: Medium | N11: Flag for review / light smoothing
A12: Moy Materials (UK) Limited | B12: 26 | C12: 0.57692308 | D12: 23 | E12: 0.56521739 | F12: 0.47346872 | G12: 141.62529 | H12: 347.84615 | I12: 273 | J12: 402 | K12: 0.47826087 | L12: 0.47826087 | M12: Medium | N12: Adopt smoothing by default
A13: Triflex (U.K.) Limited | B13: 24 | C13: 0.375 | D13: 22 | E13: 0.36363636 | F13: 0.36569416 | G13: 60.402079 | H13: 121.125 | I13: 97.5 | J13: 170.5 | K13: 0.18181818 | L13: 0.090909091 | M13: Medium | N13: Flag for review / light smoothing
A14: Westwood Liquid Technologies Limited | B14: 25 | C14: 0.32 | D14: 20 | E14: 0.3 | F14: 0.33397887 | G14: 51.722183 | H14: 83.5 | I14: 77.5 | J14: 99.25 | K14: 0.15 | L14: 0 | M14: Medium | N14: Flag for review / light smoothing
A15: FATRA UK LTD | B15: 25 | C15: 0.32 | D15: 17 | E15: 0.41176471 | F15: 0.38808527 | G15: 59.915874 | H15: 92.714286 | I15: 61 | J15: 73 | K15: 0.058823529 | L15: 0.058823529 | M15: Medium | N15: Flag for review / light smoothing
A16: Roofbase Limited | B16: 12 | C16: 0 | D16: 12 | E16: 0 | F16: 0.22997359 | G16: 48.996479 | H16: 0 | I16: 0 | J16: 0 | K16: 0 | L16: 0 | M16: Low | N16: No default smoothing
... A177: steadfast Constructionltd | B177: 2 | C177: 0 | D177: 1 | E177: 0 | F177: 0.35043595 | G177: 74.661301 | H177: 0 | I177: 0 | J177: 0 | K177: 0 | L177: 0 | M177: Very low | N177: Weak signal only
A178: A.Baul Roofing | B178: 2 | C178: 0 | D178: 0 | F178: 0.36795775 | G178: 78.394366 | H178: 0 | I178: 0 | J178: 0 | M178: Very low | N178: Weak signal only
A179: ALB Waterproofing Ltd | B179: 1 | C179: 0 | D179: 0 | F179: 0.36795775 | G179: 78.394366 | H179: 0 | I179: 0 | J179: 0 | M179: Very low | N179: Weak signal only
A180: Artisan Roofing SW Limited | B180: 1 | C180: 0 | D180: 0 | F180: 0.36795775 | G180: 78.394366 | H180: 0 | I180: 0 | J180: 0 | M180: Very low | N180: Weak signal only
A181: Artizan Roofing Limited | B181: 1 | C181: 0 | D181: 0 | F181: 0.36795775 | G181: 78.394366 | H181: 0 | I181: 0 | J181: 0 | M181: Very low | N181: Weak signal only
A182: Cambridge Roofers Ltd | B182: 1 | C182: 0 | D182: 0 | F182: 0.36795775 | G182: 78.394366 | H182: 0 | I182: 0 | J182: 0 | M182: Very low | N182: Weak signal only
A183: DHP Roofing LTD | B183: 1 | C183: 0 | D183: 0 | F183: 0.36795775 | G183: 78.394366 | H183: 0 | I183: 0 | J183: 0 | M183: Very low | N183: Weak signal only
A184: Dataload | B184: 1 | C184: 0 | D184: 0 | F184: 0.36795775 | G184: 78.394366 | H184: 0 | I184: 0 | J184: 0 | M184: Very low | N184: Weak signal only
A185: GentleCraft Limited | B185: 1 | C185: 1 | D185: 0 | F185: 0.36795775 | G185: 78.394366 | H185: 0 | I185: 0 | J185: 0 | M185: Very low | N185: Weak signal only
A186: Gribben Roofing Ltd | B186: 1 | C186: 1 | D186: 0 | F186: 0.36795775 | G186: 78.394366 | H186: 0 | I186: 0 | J186: 0 | M186: Very low | N186: Weak signal only
A187: JJ Roofing Supplies Limited | B187: 1 | C187: 0 | D187: 0 | F187: 0.36795775 | G187: 78.394366 | H187: 0 | I187: 0 | J187: 0 | M187: Very low | N187: Weak signal only
A188: M.K.M Building Supplies (Holdings) Limited | B188: 1 | C188: 0 | D188: 0 | F188: 0.36795775 | G188: 78.394366 | H188: 0 | I188: 0 | J188: 0 | M188: Very low | N188: Weak signal only
A189: Polyglass | B189: 1 | C189: 0 | D189: 0 | F189: 0.36795775 | G189: 78.394366 | H189: 0 | I189: 0 | J189: 0 | M189: Very low | N189: Weak signal only
... A198: Williams Roofing Contracts Limited | B198: 1 | C198: 0 | D198: 0 | F198: 0.36795775 | G198: 78.394366 | H198: 0 | I198: 0 | J198: 0 | M198: Very low | N198: Weak signal only

Sheet Future_Scoring
A1: Future Project Smoothing Scoring Template
A2: Paste future projects from row 5 downward. The model weights Category 30%, Type 10%, Product 30%, Account 30%. Unknown values fall back to the mature portfolio average.
A3: Global mature smoothed % | B3: 0.36795775 | C3: Global mature expected spread days | D3: 78.394366
A5: Future Project ID | B5: Project Name | C5: Category / Sector | D5: Type | E5: Main Product | F5: Account / Customer | G5: Category Rate | H5: Type Rate | I5: Product Rate | J5: Account Rate | K5: Combined Smoothed % | L5: Expected Spread Days | M5: Risk Band | N5: Suggested Treatment
G6: =IF($C6="","",IFERROR(_xludf.XLOOKUP($C6,Category_Summary!$A$5:$A$18,Category_Summary!$F$5:$F$18,$B$3),$B$3)) | H6: =IF($D6="","",IFERROR(_xludf.XLOOKUP($D6,Type_Summary!$A$5:$A$6,Type_Summary!$F$5:$F$6,$B$3),$B$3)) | I6: =IF($E6="","",IFERROR(_xludf.XLOOKUP($E6,Product_Summary!$A$5:$A$32,Product_Summary!$F$5:$F$32,$B$3),$B$3)) | J6: =IF($F6="","",IFERROR(_xludf.XLOOKUP($F6,Account_Summary!$A$5:$A$198,Account_Summary!$F$5:$F$198,$B$3),$B$3)) | K6: =IF(LEN(TRIM($C6&$D6&$E6&$F6))=0,"",SUM($G6*0.3,$H6*0.1,$I6*0.3,$J6*0.3)) | L6: =IF(LEN(TRIM($C6&$D6&$E6&$F6))=0,"",SUM(IFERROR(_xludf.XLOOKUP($C6,Category_Summary!$A$5:$A$18,Category_Summary!$G$5:$G$18,$D$3),$D$3)*0.3,IFERROR(_xludf.XLOOKUP($D6,Type_Summary!$A$5:$A$6,Type_Summary!$G$5:$G$6,$D$3),$D$3)*0.1,IFERROR(_xludf.XLOOKUP($E6,Product_Summary!$A$5:$A$32,Product_Summary!$G$5:$G$32,$D$3),$D$3)*0.3,IFERROR(_xludf.XLOOKUP($F6,Account_Summary!$A$5:$A$198,Account_Summary!$G$5:$G$198,$D$3),$D$3)*0.3)) | M6: =IF($K6="","",_xludf.IFS($K6>=0.55,"Very High",$K6>=0.45,"High",$K6>=0.35,"Moderate",TRUE,"Low")) | N6: =IF($K6="","",_xludf.IFS($K6>=0.55,"Adopt smoothing by default; phase forecast over expected days and test P75/P90 sensitivity.",$K6>=0.45,"Model a smoothing scenario; use expected spread days in forecast.",$K6>=0.35,"Flag for commercial review; apply light smoothing if project-specific evidence supports it.",TRUE,"No default smoothing; assume short/same-day spread unless contract/customer evidence changes."))
G7: =IF($C7="","",IFERROR(_xludf.XLOOKUP($C7,Category_Summary!$A$5:$A$18,Category_Summary!$F$5:$F$18,$B$3),$B$3)) | H7: =IF($D7="","",IFERROR(_xludf.XLOOKUP($D7,Type_Summary!$A$5:$A$6,Type_Summary!$F$5:$F$6,$B$3),$B$3)) | I7: =IF($E7="","",IFERROR(_xludf.XLOOKUP($E7,Product_Summary!$A$5:$A$32,Product_Summary!$F$5:$F$32,$B$3),$B$3)) | J7: =IF($F7="","",IFERROR(_xludf.XLOOKUP($F7,Account_Summary!$A$5:$A$198,Account_Summary!$F$5:$F$198,$B$3),$B$3)) | K7: =IF(LEN(TRIM($C7&$D7&$E7&$F7))=0,"",SUM($G7*0.3,$H7*0.1,$I7*0.3,$J7*0.3)) | L7: =IF(LEN(TRIM($C7&$D7&$E7&$F7))=0,"",SUM(IFERROR(_xludf.XLOOKUP($C7,Category_Summary!$A$5:$A$18,Category_Summary!$G$5:$G$18,$D$3),$D$3)*0.3,IFERROR(_xludf.XLOOKUP($D7,Type_Summary!$A$5:$A$6,Type_Summary!$G$5:$G$6,$D$3),$D$3)*0.1,IFERROR(_xludf.XLOOKUP($E7,Product_Summary!$A$5:$A$32,Product_Summary!$G$5:$G$32,$D$3),$D$3)*0.3,IFERROR(_xludf.XLOOKUP($F7,Account_Summary!$A$5:$A$198,Account_Summary!$G$5:$G$198,$D$3),$D$3)*0.3)) | M7: =IF($K7="","",_xludf.IFS($K7>=0.55,"Very High",$K7>=0.45,"High",$K7>=0.35,"Moderate",TRUE,"Low")) | N7: =IF($K7="","",_xludf.IFS($K7>=0.55,"Adopt smoothing by default; phase forecast over expected days and test P75/P90 sensitivity.",$K7>=0.45,"Model a smoothing scenario; use expected spread days in forecast.",$K7>=0.35,"Flag for commercial review; apply light smoothing if project-specific evidence supports it.",TRUE,"No default smoothing; assume short/same-day spread unless contract/customer evidence changes."))
G8: =IF($C8="","",IFERROR(_xludf.XLOOKUP($C8,Category_Summary!$A$5:$A$18,Category_Summary!$F$5:$F$18,$B$3),$B$3)) | H8: =IF($D8="","",IFERROR(_xludf.XLOOKUP($D8,Type_Summary!$A$5:$A$6,Type_Summary!$F$5:$F$6,$B$3),$B$3)) | I8: =IF($E8="","",IFERROR(_xludf.XLOOKUP($E8,Product_Summary!$A$5:$A$32,Product_Summary!$F$5:$F$32,$B$3),$B$3)) | J8: =IF($F8="","",IFERROR(_xludf.XLOOKUP($F8,Account_Summary!$A$5:$A$198,Account_Summary!$F$5:$F$198,$B$3),$B$3)) | K8: =IF(LEN(TRIM($C8&$D8&$E8&$F8))=0,"",SUM($G8*0.3,$H8*0.1,$I8*0.3,$J8*0.3)) | L8: =IF(LEN(TRIM($C8&$D8&$E8&$F8))=0,"",SUM(IFERROR(_xludf.XLOOKUP($C8,Category_Summary!$A$5:$A$18,Category_Summary!$G$5:$G$18,$D$3),$D$3)*0.3,IFERROR(_xludf.XLOOKUP($D8,Type_Summary!$A$5:$A$6,Type_Summary!$G$5:$G$6,$D$3),$D$3)*0.1,IFERROR(_xludf.XLOOKUP($E8,Product_Summary!$A$5:$A$32,Product_Summary!$G$5:$G$32,$D$3),$D$3)*0.3,IFERROR(_xludf.XLOOKUP($F8,Account_Summary!$A$5:$A$198,Account_Summary!$G$5:$G$198,$D$3),$D$3)*0.3)) | M8: =IF($K8="","",_xludf.IFS($K8>=0.55,"Very High",$K8>=0.45,"High",$K8>=0.35,"Moderate",TRUE,"Low")) | N8: =IF($K8="","",_xludf.IFS($K8>=0.55,"Adopt smoothing by default; phase forecast over expected days and test P75/P90 sensitivity.",$K8>=0.45,"Model a smoothing scenario; use expected spread days in forecast.",$K8>=0.35,"Flag for commercial review; apply light smoothing if project-specific evidence supports it.",TRUE,"No default smoothing; assume short/same-day spread unless contract/customer evidence changes."))
G9: =IF($C9="","",IFERROR(_xludf.XLOOKUP($C9,Category_Summary!$A$5:$A$18,Category_Summary!$F$5:$F$18,$B$3),$B$3)) | H9: =IF($D9="","",IFERROR(_xludf.XLOOKUP($D9,Type_Summary!$A$5:$A$6,Type_Summary!$F$5:$F$6,$B$3),$B$3)) | I9: =IF($E9="","",IFERROR(_xludf.XLOOKUP($E9,Product_Summary!$A$5:$A$32,Product_Summary!$F$5:$F$32,$B$3),$B$3)) | J9: =IF($F9="","",IFERROR(_xludf.XLOOKUP($F9,Account_Summary!$A$5:$A$198,Account_Summary!$F$5:$F$198,$B$3),$B$3)) | K9: =IF(LEN(TRIM($C9&$D9&$E9&$F9))=0,"",SUM($G9*0.3,$H9*0.1,$I9*0.3,$J9*0.3)) | L9: =IF(LEN(TRIM($C9&$D9&$E9&$F9))=0,"",SUM(IFERROR(_xludf.XLOOKUP($C9,Category_Summary!$A$5:$A$18,Category_Summary!$G$5:$G$18,$D$3),$D$3)*0.3,IFERROR(_xludf.XLOOKUP($D9,Type_Summary!$A$5:$A$6,Type_Summary!$G$5:$G$6,$D$3),$D$3)*0.1,IFERROR(_xludf.XLOOKUP($E9,Product_Summary!$A$5:$A$32,Product_Summary!$G$5:$G$32,$D$3),$D$3)*0.3,IFERROR(_xludf.XLOOKUP($F9,Account_Summary!$A$5:$A$198,Account_Summary!$G$5:$G$198,$D$3),$D$3)*0.3)) | M9: =IF($K9="","",_xludf.IFS($K9>=0.55,"Very High",$K9>=0.45,"High",$K9>=0.35,"Moderate",TRUE,"Low")) | N9: =IF($K9="","",_xludf.IFS($K9>=0.55,"Adopt smoothing by default; phase forecast over expected days and test P75/P90 sensitivity.",$K9>=0.45,"Model a smoothing scenario; use expected spread days in forecast.",$K9>=0.35,"Flag for commercial review; apply light smoothing if project-specific evidence supports it.",TRUE,"No default smoothing; assume short/same-day spread unless contract/customer evidence changes."))
G10: =IF($C10="","",IFERROR(_xludf.XLOOKUP($C10,Category_Summary!$A$5:$A$18,Category_Summary!$F$5:$F$18,$B$3),$B$3)) | H10: =IF($D10="","",IFERROR(_xludf.XLOOKUP($D10,Type_Summary!$A$5:$A$6,Type_Summary!$F$5:$F$6,$B$3),$B$3)) | I10: =IF($E10="","",IFERROR(_xludf.XLOOKUP($E10,Product_Summary!$A$5:$A$32,Product_Summary!$F$5:$F$32,$B$3),$B$3)) | J10: =IF($F10="","",IFERROR(_xludf.XLOOKUP($F10,Account_Summary!$A$5:$A$198,Account_Summary!$F$5:$F$198,$B$3),$B$3)) | K10: =IF(LEN(TRIM($C10&$D10&$E10&$F10))=0,"",SUM($G10*0.3,$H10*0.1,$I10*0.3,$J10*0.3)) | L10: =IF(LEN(TRIM($C10&$D10&$E10&$F10))=0,"",SUM(IFERROR(_xludf.XLOOKUP($C10,Category_Summary!$A$5:$A$18,Category_Summary!$G$5:$G$18,$D$3),$D$3)*0.3,IFERROR(_xludf.XLOOKUP($D10,Type_Summary!$A$5:$A$6,Type_Summary!$G$5:$G$6,$D$3),$D$3)*0.1,IFERROR(_xludf.XLOOKUP($E10,Product_Summary!$A$5:$A$32,Product_Summary!$G$5:$G$32,$D$3),$D$3)*0.3,IFERROR(_xludf.XLOOKUP($F10,Account_Summary!$A$5:$A$198,Account_Summary!$G$5:$G$198,$D$3),$D$3)*0.3)) | M10: =IF($K10="","",_xludf.IFS($K10>=0.55,"Very High",$K10>=0.45,"High",$K10>=0.35,"Moderate",TRUE,"Low")) | N10: =IF($K10="","",_xludf.IFS($K10>=0.55,"Adopt smoothing by default; phase forecast over expected days and test P75/P90 sensitivity.",$K10>=0.45,"Model a smoothing scenario; use expected spread days in forecast.",$K10>=0.35,"Flag for commercial review; apply light smoothing if project-specific evidence supports it.",TRUE,"No default smoothing; assume short/same-day spread unless contract/customer evidence changes."))
G11: =IF($C11="","",IFERROR(_xludf.XLOOKUP($C11,Category_Summary!$A$5:$A$18,Category_Summary!$F$5:$F$18,$B$3),$B$3)) | H11: =IF($D11="","",IFERROR(_xludf.XLOOKUP($D11,Type_Summary!$A$5:$A$6,Type_Summary!$F$5:$F$6,$B$3),$B$3)) | I11: =IF($E11="","",IFERROR(_xludf.XLOOKUP($E11,Product_Summary!$A$5:$A$32,Product_Summary!$F$5:$F$32,$B$3),$B$3)) | J11: =IF($F11="","",IFERROR(_xludf.XLOOKUP($F11,Account_Summary!$A$5:$A$198,Account_Summary!$F$5:$F$198,$B$3),$B$3)) | K11: =IF(LEN(TRIM($C11&$D11&$E11&$F11))=0,"",SUM($G11*0.3,$H11*0.1,$I11*0.3,$J11*0.3)) | L11: =IF(LEN(TRIM($C11&$D11&$E11&$F11))=0,"",SUM(IFERROR(_xludf.XLOOKUP($C11,Category_Summary!$A$5:$A$18,Category_Summary!$G$5:$G$18,$D$3),$D$3)*0.3,IFERROR(_xludf.XLOOKUP($D11,Type_Summary!$A$5:$A$6,Type_Summary!$G$5:$G$6,$D$3),$D$3)*0.1,IFERROR(_xludf.XLOOKUP($E11,Product_Summary!$A$5:$A$32,Product_Summary!$G$5:$G$32,$D$3),$D$3)*0.3,IFERROR(_xludf.XLOOKUP($F11,Account_Summary!$A$5:$A$198,Account_Summary!$G$5:$G$198,$D$3),$D$3)*0.3)) | M11: =IF($K11="","",_xludf.IFS($K11>=0.55,"Very High",$K11>=0.45,"High",$K11>=0.35,"Moderate",TRUE,"Low")) | N11: =IF($K11="","",_xludf.IFS($K11>=0.55,"Adopt smoothing by default; phase forecast over expected days and test P75/P90 sensitivity.",$K11>=0.45,"Model a smoothing scenario; use expected spread days in forecast.",$K11>=0.35,"Flag for commercial review; apply light smoothing if project-specific evidence supports it.",TRUE,"No default smoothing; assume short/same-day spread unless contract/customer evidence changes."))
G12: =IF($C12="","",IFERROR(_xludf.XLOOKUP($C12,Category_Summary!$A$5:$A$18,Category_Summary!$F$5:$F$18,$B$3),$B$3)) | H12: =IF($D12="","",IFERROR(_xludf.XLOOKUP($D12,Type_Summary!$A$5:$A$6,Type_Summary!$F$5:$F$6,$B$3),$B$3)) | I12: =IF($E12="","",IFERROR(_xludf.XLOOKUP($E12,Product_Summary!$A$5:$A$32,Product_Summary!$F$5:$F$32,$B$3),$B$3)) | J12: =IF($F12="","",IFERROR(_xludf.XLOOKUP($F12,Account_Summary!$A$5:$A$198,Account_Summary!$F$5:$F$198,$B$3),$B$3)) | K12: =IF(LEN(TRIM($C12&$D12&$E12&$F12))=0,"",SUM($G12*0.3,$H12*0.1,$I12*0.3,$J12*0.3)) | L12: =IF(LEN(TRIM($C12&$D12&$E12&$F12))=0,"",SUM(IFERROR(_xludf.XLOOKUP($C12,Category_Summary!$A$5:$A$18,Category_Summary!$G$5:$G$18,$D$3),$D$3)*0.3,IFERROR(_xludf.XLOOKUP($D12,Type_Summary!$A$5:$A$6,Type_Summary!$G$5:$G$6,$D$3),$D$3)*0.1,IFERROR(_xludf.XLOOKUP($E12,Product_Summary!$A$5:$A$32,Product_Summary!$G$5:$G$32,$D$3),$D$3)*0.3,IFERROR(_xludf.XLOOKUP($F12,Account_Summary!$A$5:$A$198,Account_Summary!$G$5:$G$198,$D$3),$D$3)*0.3)) | M12: =IF($K12="","",_xludf.IFS($K12>=0.55,"Very High",$K12>=0.45,"High",$K12>=0.35,"Moderate",TRUE,"Low")) | N12: =IF($K12="","",_xludf.IFS($K12>=0.55,"Adopt smoothing by default; phase forecast over expected days and test P75/P90 sensitivity.",$K12>=0.45,"Model a smoothing scenario; use expected spread days in forecast.",$K12>=0.35,"Flag for commercial review; apply light smoothing if project-specific evidence supports it.",TRUE,"No default smoothing; assume short/same-day spread unless contract/customer evidence changes."))
G13: =IF($C13="","",IFERROR(_xludf.XLOOKUP($C13,Category_Summary!$A$5:$A$18,Category_Summary!$F$5:$F$18,$B$3),$B$3)) | H13: =IF($D13="","",IFERROR(_xludf.XLOOKUP($D13,Type_Summary!$A$5:$A$6,Type_Summary!$F$5:$F$6,$B$3),$B$3)) | I13: =IF($E13="","",IFERROR(_xludf.XLOOKUP($E13,Product_Summary!$A$5:$A$32,Product_Summary!$F$5:$F$32,$B$3),$B$3)) | J13: =IF($F13="","",IFERROR(_xludf.XLOOKUP($F13,Account_Summary!$A$5:$A$198,Account_Summary!$F$5:$F$198,$B$3),$B$3)) | K13: =IF(LEN(TRIM($C13&$D13&$E13&$F13))=0,"",SUM($G13*0.3,$H13*0.1,$I13*0.3,$J13*0.3)) | L13: =IF(LEN(TRIM($C13&$D13&$E13&$F13))=0,"",SUM(IFERROR(_xludf.XLOOKUP($C13,Category_Summary!$A$5:$A$18,Category_Summary!$G$5:$G$18,$D$3),$D$3)*0.3,IFERROR(_xludf.XLOOKUP($D13,Type_Summary!$A$5:$A$6,Type_Summary!$G$5:$G$6,$D$3),$D$3)*0.1,IFERROR(_xludf.XLOOKUP($E13,Product_Summary!$A$5:$A$32,Product_Summary!$G$5:$G$32,$D$3),$D$3)*0.3,IFERROR(_xludf.XLOOKUP($F13,Account_Summary!$A$5:$A$198,Account_Summary!$G$5:$G$198,$D$3),$D$3)*0.3)) | M13: =IF($K13="","",_xludf.IFS($K13>=0.55,"Very High",$K13>=0.45,"High",$K13>=0.35,"Moderate",TRUE,"Low")) | N13: =IF($K13="","",_xludf.IFS($K13>=0.55,"Adopt smoothing by default; phase forecast over expected days and test P75/P90 sensitivity.",$K13>=0.45,"Model a smoothing scenario; use expected spread days in forecast.",$K13>=0.35,"Flag for commercial review; apply light smoothing if project-specific evidence supports it.",TRUE,"No default smoothing; assume short/same-day spread unless contract/customer evidence changes."))
G14: =IF($C14="","",IFERROR(_xludf.XLOOKUP($C14,Category_Summary!$A$5:$A$18,Category_Summary!$F$5:$F$18,$B$3),$B$3)) | H14: =IF($D14="","",IFERROR(_xludf.XLOOKUP($D14,Type_Summary!$A$5:$A$6,Type_Summary!$F$5:$F$6,$B$3),$B$3)) | I14: =IF($E14="","",IFERROR(_xludf.XLOOKUP($E14,Product_Summary!$A$5:$A$32,Product_Summary!$F$5:$F$32,$B$3),$B$3)) | J14: =IF($F14="","",IFERROR(_xludf.XLOOKUP($F14,Account_Summary!$A$5:$A$198,Account_Summary!$F$5:$F$198,$B$3),$B$3)) | K14: =IF(LEN(TRIM($C14&$D14&$E14&$F14))=0,"",SUM($G14*0.3,$H14*0.1,$I14*0.3,$J14*0.3)) | L14: =IF(LEN(TRIM($C14&$D14&$E14&$F14))=0,"",SUM(IFERROR(_xludf.XLOOKUP($C14,Category_Summary!$A$5:$A$18,Category_Summary!$G$5:$G$18,$D$3),$D$3)*0.3,IFERROR(_xludf.XLOOKUP($D14,Type_Summary!$A$5:$A$6,Type_Summary!$G$5:$G$6,$D$3),$D$3)*0.1,IFERROR(_xludf.XLOOKUP($E14,Product_Summary!$A$5:$A$32,Product_Summary!$G$5:$G$32,$D$3),$D$3)*0.3,IFERROR(_xludf.XLOOKUP($F14,Account_Summary!$A$5:$A$198,Account_Summary!$G$5:$G$198,$D$3),$D$3)*0.3)) | M14: =IF($K14="","",_xludf.IFS($K14>=0.55,"Very High",$K14>=0.45,"High",$K14>=0.35,"Moderate",TRUE,"Low")) | N14: =IF($K14="","",_xludf.IFS($K14>=0.55,"Adopt smoothing by default; phase forecast over expected days and test P75/P90 sensitivity.",$K14>=0.45,"Model a smoothing scenario; use expected spread days in forecast.",$K14>=0.35,"Flag for commercial review; apply light smoothing if project-specific evidence supports it.",TRUE,"No default smoothing; assume short/same-day spread unless contract/customer evidence changes."))
G15: =IF($C15="","",IFERROR(_xludf.XLOOKUP($C15,Category_Summary!$A$5:$A$18,Category_Summary!$F$5:$F$18,$B$3),$B$3)) | H15: =IF($D15="","",IFERROR(_xludf.XLOOKUP($D15,Type_Summary!$A$5:$A$6,Type_Summary!$F$5:$F$6,$B$3),$B$3)) | I15: =IF($E15="","",IFERROR(_xludf.XLOOKUP($E15,Product_Summary!$A$5:$A$32,Product_Summary!$F$5:$F$32,$B$3),$B$3)) | J15: =IF($F15="","",IFERROR(_xludf.XLOOKUP($F15,Account_Summary!$A$5:$A$198,Account_Summary!$F$5:$F$198,$B$3),$B$3)) | K15: =IF(LEN(TRIM($C15&$D15&$E15&$F15))=0,"",SUM($G15*0.3,$H15*0.1,$I15*0.3,$J15*0.3)) | L15: =IF(LEN(TRIM($C15&$D15&$E15&$F15))=0,"",SUM(IFERROR(_xludf.XLOOKUP($C15,Category_Summary!$A$5:$A$18,Category_Summary!$G$5:$G$18,$D$3),$D$3)*0.3,IFERROR(_xludf.XLOOKUP($D15,Type_Summary!$A$5:$A$6,Type_Summary!$G$5:$G$6,$D$3),$D$3)*0.1,IFERROR(_xludf.XLOOKUP($E15,Product_Summary!$A$5:$A$32,Product_Summary!$G$5:$G$32,$D$3),$D$3)*0.3,IFERROR(_xludf.XLOOKUP($F15,Account_Summary!$A$5:$A$198,Account_Summary!$G$5:$G$198,$D$3),$D$3)*0.3)) | M15: =IF($K15="","",_xludf.IFS($K15>=0.55,"Very High",$K15>=0.45,"High",$K15>=0.35,"Moderate",TRUE,"Low")) | N15: =IF($K15="","",_xludf.IFS($K15>=0.55,"Adopt smoothing by default; phase forecast over expected days and test P75/P90 sensitivity.",$K15>=0.45,"Model a smoothing scenario; use expected spread days in forecast.",$K15>=0.35,"Flag for commercial review; apply light smoothing if project-specific evidence supports it.",TRUE,"No default smoothing; assume short/same-day spread unless contract/customer evidence changes."))
G16: =IF($C16="","",IFERROR(_xludf.XLOOKUP($C16,Category_Summary!$A$5:$A$18,Category_Summary!$F$5:$F$18,$B$3),$B$3)) | H16: =IF($D16="","",IFERROR(_xludf.XLOOKUP($D16,Type_Summary!$A$5:$A$6,Type_Summary!$F$5:$F$6,$B$3),$B$3)) | I16: =IF($E16="","",IFERROR(_xludf.XLOOKUP($E16,Product_Summary!$A$5:$A$32,Product_Summary!$F$5:$F$32,$B$3),$B$3)) | J16: =IF($F16="","",IFERROR(_xludf.XLOOKUP($F16,Account_Summary!$A$5:$A$198,Account_Summary!$F$5:$F$198,$B$3),$B$3)) | K16: =IF(LEN(TRIM($C16&$D16&$E16&$F16))=0,"",SUM($G16*0.3,$H16*0.1,$I16*0.3,$J16*0.3)) | L16: =IF(LEN(TRIM($C16&$D16&$E16&$F16))=0,"",SUM(IFERROR(_xludf.XLOOKUP($C16,Category_Summary!$A$5:$A$18,Category_Summary!$G$5:$G$18,$D$3),$D$3)*0.3,IFERROR(_xludf.XLOOKUP($D16,Type_Summary!$A$5:$A$6,Type_Summary!$G$5:$G$6,$D$3),$D$3)*0.1,IFERROR(_xludf.XLOOKUP($E16,Product_Summary!$A$5:$A$32,Product_Summary!$G$5:$G$32,$D$3),$D$3)*0.3,IFERROR(_xludf.XLOOKUP($F16,Account_Summary!$A$5:$A$198,Account_Summary!$G$5:$G$198,$D$3),$D$3)*0.3)) | M16: =IF($K16="","",_xludf.IFS($K16>=0.55,"Very High",$K16>=0.45,"High",$K16>=0.35,"Moderate",TRUE,"Low")) | N16: =IF($K16="","",_xludf.IFS($K16>=0.55,"Adopt smoothing by default; phase forecast over expected days and test P75/P90 sensitivity.",$K16>=0.45,"Model a smoothing scenario; use expected spread days in forecast.",$K16>=0.35,"Flag for commercial review; apply light smoothing if project-specific evidence supports it.",TRUE,"No default smoothing; assume short/same-day spread unless contract/customer evidence changes."))
G17: =IF($C17="","",IFERROR(_xludf.XLOOKUP($C17,Category_Summary!$A$5:$A$18,Category_Summary!$F$5:$F$18,$B$3),$B$3)) | H17: =IF($D17="","",IFERROR(_xludf.XLOOKUP($D17,Type_Summary!$A$5:$A$6,Type_Summary!$F$5:$F$6,$B$3),$B$3)) | I17: =IF($E17="","",IFERROR(_xludf.XLOOKUP($E17,Product_Summary!$A$5:$A$32,Product_Summary!$F$5:$F$32,$B$3),$B$3)) | J17: =IF($F17="","",IFERROR(_xludf.XLOOKUP($F17,Account_Summary!$A$5:$A$198,Account_Summary!$F$5:$F$198,$B$3),$B$3)) | K17: =IF(LEN(TRIM($C17&$D17&$E17&$F17))=0,"",SUM($G17*0.3,$H17*0.1,$I17*0.3,$J17*0.3)) | L17: =IF(LEN(TRIM($C17&$D17&$E17&$F17))=0,"",SUM(IFERROR(_xludf.XLOOKUP($C17,Category_Summary!$A$5:$A$18,Category_Summary!$G$5:$G$18,$D$3),$D$3)*0.3,IFERROR(_xludf.XLOOKUP($D17,Type_Summary!$A$5:$A$6,Type_Summary!$G$5:$G$6,$D$3),$D$3)*0.1,IFERROR(_xludf.XLOOKUP($E17,Product_Summary!$A$5:$A$32,Product_Summary!$G$5:$G$32,$D$3),$D$3)*0.3,IFERROR(_xludf.XLOOKUP($F17,Account_Summary!$A$5:$A$198,Account_Summary!$G$5:$G$198,$D$3),$D$3)*0.3)) | M17: =IF($K17="","",_xludf.IFS($K17>=0.55,"Very High",$K17>=0.45,"High",$K17>=0.35,"Moderate",TRUE,"Low")) | N17: =IF($K17="","",_xludf.IFS($K17>=0.55,"Adopt smoothing by default; phase forecast over expected days and test P75/P90 sensitivity.",$K17>=0.45,"Model a smoothing scenario; use expected spread days in forecast.",$K17>=0.35,"Flag for commercial review; apply light smoothing if project-specific evidence supports it.",TRUE,"No default smoothing; assume short/same-day spread unless contract/customer evidence changes."))
... G105: =IF($C105="","",IFERROR(_xludf.XLOOKUP($C105,Category_Summary!$A$5:$A$18,Category_Summary!$F$5:$F$18,$B$3),$B$3)) | H105: =IF($D105="","",IFERROR(_xludf.XLOOKUP($D105,Type_Summary!$A$5:$A$6,Type_Summary!$F$5:$F$6,$B$3),$B$3)) | I105: =IF($E105="","",IFERROR(_xludf.XLOOKUP($E105,Product_Summary!$A$5:$A$32,Product_Summary!$F$5:$F$32,$B$3),$B$3)) | J105: =IF($F105="","",IFERROR(_xludf.XLOOKUP($F105,Account_Summary!$A$5:$A$198,Account_Summary!$F$5:$F$198,$B$3),$B$3)) | K105: =IF(LEN(TRIM($C105&$D105&$E105&$F105))=0,"",SUM($G105*0.3,$H105*0.1,$I105*0.3,$J105*0.3)) | L105: =IF(LEN(TRIM($C105&$D105&$E105&$F105))=0,"",SUM(IFERROR(_xludf.XLOOKUP($C105,Category_Summary!$A$5:$A$18,Category_Summary!$G$5:$G$18,$D$3),$D$3)*0.3,IFERROR(_xludf.XLOOKUP($D105,Type_Summary!$A$5:$A$6,Type_Summary!$G$5:$G$6,$D$3),$D$3)*0.1,IFERROR(_xludf.XLOOKUP($E105,Product_Summary!$A$5:$A$32,Product_Summary!$G$5:$G$32,$D$3),$D$3)*0.3,IFERROR(_xludf.XLOOKUP($F105,Account_Summary!$A$5:$A$198,Account_Summary!$G$5:$G$198,$D$3),$D$3)*0.3)) | M105: =IF($K105="","",_xludf.IFS($K105>=0.55,"Very High",$K105>=0.45,"High",$K105>=0.35,"Moderate",TRUE,"Low")) | N105: =IF($K105="","",_xludf.IFS($K105>=0.55,"Adopt smoothing by default; phase forecast over expected days and test P75/P90 sensitivity.",$K105>=0.45,"Model a smoothing scenario; use expected spread days in forecast.",$K105>=0.35,"Flag for commercial review; apply light smoothing if project-specific evidence supports it.",TRUE,"No default smoothing; assume short/same-day spread unless contract/customer evidence changes."))

Sheet Methodology
A1: Methodology and assumptions
A2: Definition of smoothing | B2: A project is treated as smoothed when Invoicing spread (DAYS) > 0, equivalent to Last Date Invoiced later than First Date Invoiced.
A3: Why mature cohort is used | B3: Recent projects can be right-censored: they may look unsmoothed only because later invoices have not occurred yet. The template therefore uses projects whose first invoice date is at least 180 days before the workbook date context.
A4: Mature cohort cut-off | B4: Analysis date (28 April 2026) - 180 days = 2025-10-30
A5: Shrinkage logic | B5: Group-level rates are shrunk toward the mature portfolio average using k = 20 pseudo-projects. This stops small categories, products, or accounts from dominating the forecast.
A6: Shrunk smoothed % | B6: (Mature smoothed count + 20 × mature portfolio smoothed %) ÷ (Mature project count + 20).
A7: Expected spread days | B7: (Mature group spread-days sum + 20 × mature portfolio average spread) ÷ (Mature project count + 20).
A8: Future scoring weights | B8: Category 30%, Type 10%, Product 30%, Account 30%. Type receives a lower weight because New Build and Refurbishment show very similar smoothing rates.
A9: Suggested use thresholds | B9: Very High ≥55%; High ≥45%; Moderate ≥35%; Low <35%. Separately, groups with expected spread around 120+ days should normally be smoothed even if probability is moderate.
A10: Main caveat | B10: There is no project value/revenue column in the source workbook, so the model predicts invoice timing tendency, not revenue-weighted smoothing impact.
A11: Recommended next enhancement | B11: Add contract value, planned invoice profile, expected project duration, PM/customer, and forecast period. These would allow a revenue-weighted smoothing model rather than a count-based model.
B13: Algorithm summary (Empirical-Bayes-shrunk weighted scorecard model)
B14: 1. Calculate invoice spread days for each historic project.
B16: 2. Mark each historic project as smoothed or not smoothed:
B17: Smoothed = 1 if spread days > 0
B18: Smoothed = 0 if spread days = 0
B20: 3. Filter to mature projects to reduce distortion from recent unfinished projects.
B22: 4. Calculate the global mature smoothing rate and global mature expected spread.
B24: 5. For each category, type, product, and account:
B25: Calculate raw smoothing rate.
B26: Calculate raw expected spread days.
B27: Apply shrinkage toward the global average.
B29: 6. For a future project:
... B48: Suggested forecasting treatment.
A52: Summary sheet | B52: What it measures
A53: Category_Summary | B53: Smoothing behaviour by sector/category
A54: Type_Summary | B54: Smoothing behaviour by project type
A55: Category_Type_Summary | B55: Smoothing behaviour for combinations such as Education + Refurbishment
A56: Product_Summary | B56: Smoothing behaviour by product
A57: Account_Summary | B57: Smoothing behaviour by customer/account
A61: Sector Metric | B61: Meaning
A62: Mature Projects | B62: Number of mature historic projects in that group
A63: Mature Smoothed % | B63: Raw smoothing rate for that group
A64: Shrunk Mature Smoothed % | B64: Adjusted smoothing rate used by the model
A65: Mature Expected Spread Days | B65: Average invoice spread days for that group
A66: Avg Spread if Smoothed | B66: Average spread only among projects that actually smoothed
... A71: Suggested Use | B71: How strongly that group supports smoothing
